{
  "hash": "d3de59b2",
  "browserHash": "c57938ec",
  "optimized": {
    "vue": {
      "src": "../../../../../node_modules/.pnpm/vue@3.3.11/node_modules/vue/dist/vue.runtime.esm-bundler.js",
      "file": "vue.js",
      "fileHash": "8d30b609",
      "needsInterop": false
    },
    "vitepress > @vue/devtools-api": {
      "src": "../../../../../node_modules/.pnpm/@vue+devtools-api@6.5.1/node_modules/@vue/devtools-api/lib/esm/index.js",
      "file": "vitepress___@vue_devtools-api.js",
      "fileHash": "fede68e4",
      "needsInterop": false
    },
    "vitepress > @vueuse/integrations/useFocusTrap": {
      "src": "../../../../../node_modules/.pnpm/@vueuse+integrations@10.7.0_uet6d4gr6nh4t6dn63frk3g5c4/node_modules/@vueuse/integrations/useFocusTrap.mjs",
      "file": "vitepress___@vueuse_integrations_useFocusTrap.js",
      "fileHash": "d7d6d6e0",
      "needsInterop": false
    },
    "vitepress > mark.js/src/vanilla.js": {
      "src": "../../../../../node_modules/.pnpm/mark.js@8.11.1/node_modules/mark.js/src/vanilla.js",
      "file": "vitepress___mark__js_src_vanilla__js.js",
      "fileHash": "01d83290",
      "needsInterop": false
    },
    "vitepress > minisearch": {
      "src": "../../../../../node_modules/.pnpm/minisearch@6.3.0/node_modules/minisearch/dist/es/index.js",
      "file": "vitepress___minisearch.js",
      "fileHash": "1dbea27e",
      "needsInterop": false
    },
    "@vueuse/core": {
      "src": "../../../../../node_modules/.pnpm/@vueuse+core@10.7.0_vue@3.3.11/node_modules/@vueuse/core/index.mjs",
      "file": "@vueuse_core.js",
      "fileHash": "69930dbd",
      "needsInterop": false
    },
    "@tu-view-plus/icons-vue": {
      "src": "../../../../../node_modules/.pnpm/@tu-view-plus+icons-vue@1.0.1/node_modules/@tu-view-plus/icons-vue/dist/index.js",
      "file": "@tu-view-plus_icons-vue.js",
      "fileHash": "527704ae",
      "needsInterop": false
    },
    "lodash-unified": {
      "src": "../../../../../node_modules/.pnpm/lodash-unified@1.0.3_vpgwo5v3ie2bia5ss74pgoa5ly/node_modules/lodash-unified/import.js",
      "file": "lodash-unified.js",
      "fileHash": "69816f5c",
      "needsInterop": false
    },
    "async-validator": {
      "src": "../../../../../node_modules/.pnpm/async-validator@4.2.5/node_modules/async-validator/dist-web/index.js",
      "file": "async-validator.js",
      "fileHash": "a3732df8",
      "needsInterop": false
    },
    "resize-observer-polyfill": {
      "src": "../../../../../node_modules/.pnpm/resize-observer-polyfill@1.5.1/node_modules/resize-observer-polyfill/dist/ResizeObserver.es.js",
      "file": "resize-observer-polyfill.js",
      "fileHash": "fa2ce312",
      "needsInterop": false
    },
    "number-precision": {
      "src": "../../../../../node_modules/.pnpm/number-precision@1.5.0/node_modules/number-precision/build/index.es.js",
      "file": "number-precision.js",
      "fileHash": "80ecebf7",
      "needsInterop": false
    },
    "b-tween": {
      "src": "../../../../../node_modules/.pnpm/b-tween@0.3.3/node_modules/b-tween/dist/b-tween.es.js",
      "file": "b-tween.js",
      "fileHash": "1751f979",
      "needsInterop": false
    },
    "@vue/shared": {
      "src": "../../../../../node_modules/.pnpm/@vue+shared@3.3.11/node_modules/@vue/shared/dist/shared.esm-bundler.js",
      "file": "@vue_shared.js",
      "fileHash": "f25b0e29",
      "needsInterop": false
    },
    "dayjs": {
      "src": "../../../../../node_modules/.pnpm/dayjs@1.11.10/node_modules/dayjs/dayjs.min.js",
      "file": "dayjs.js",
      "fileHash": "ba6b89aa",
      "needsInterop": true
    },
    "dayjs/plugin/customParseFormat": {
      "src": "../../../../../node_modules/.pnpm/dayjs@1.11.10/node_modules/dayjs/plugin/customParseFormat.js",
      "file": "dayjs_plugin_customParseFormat.js",
      "fileHash": "26cc6d51",
      "needsInterop": true
    },
    "dayjs/plugin/isBetween": {
      "src": "../../../../../node_modules/.pnpm/dayjs@1.11.10/node_modules/dayjs/plugin/isBetween.js",
      "file": "dayjs_plugin_isBetween.js",
      "fileHash": "e8b137cc",
      "needsInterop": true
    },
    "dayjs/plugin/weekOfYear": {
      "src": "../../../../../node_modules/.pnpm/dayjs@1.11.10/node_modules/dayjs/plugin/weekOfYear.js",
      "file": "dayjs_plugin_weekOfYear.js",
      "fileHash": "819e4fb8",
      "needsInterop": true
    },
    "dayjs/plugin/advancedFormat": {
      "src": "../../../../../node_modules/.pnpm/dayjs@1.11.10/node_modules/dayjs/plugin/advancedFormat.js",
      "file": "dayjs_plugin_advancedFormat.js",
      "fileHash": "73530b47",
      "needsInterop": true
    },
    "dayjs/plugin/weekYear": {
      "src": "../../../../../node_modules/.pnpm/dayjs@1.11.10/node_modules/dayjs/plugin/weekYear.js",
      "file": "dayjs_plugin_weekYear.js",
      "fileHash": "25bf4bfa",
      "needsInterop": true
    },
    "dayjs/plugin/quarterOfYear": {
      "src": "../../../../../node_modules/.pnpm/dayjs@1.11.10/node_modules/dayjs/plugin/quarterOfYear.js",
      "file": "dayjs_plugin_quarterOfYear.js",
      "fileHash": "3ca841c6",
      "needsInterop": true
    },
    "dayjs/locale/zh-cn": {
      "src": "../../../../../node_modules/.pnpm/dayjs@1.11.10/node_modules/dayjs/locale/zh-cn.js",
      "file": "dayjs_locale_zh-cn.js",
      "fileHash": "73f27827",
      "needsInterop": true
    }
  },
  "chunks": {
    "chunk-2O7CYDOE": {
      "file": "chunk-2O7CYDOE.js"
    },
    "chunk-AA2WRIRA": {
      "file": "chunk-AA2WRIRA.js"
    },
    "chunk-7H5FDLAX": {
      "file": "chunk-7H5FDLAX.js"
    },
    "chunk-32XGVV2K": {
      "file": "chunk-32XGVV2K.js"
    },
    "chunk-76J2PTFD": {
      "file": "chunk-76J2PTFD.js"
    }
  }
}